yaraprocessor.py
yaraprocessor-1.1.0.dist-info/RECORD
yaraprocessor-1.1.0.dist-info/top_level.txt
yaraprocessor-1.1.0.dist-info/metadata.json
yaraprocessor-1.1.0.dist-info/WHEEL
yaraprocessor-1.1.0.dist-info/DESCRIPTION.rst
yaraprocessor-1.1.0.dist-info/METADATA
