Metadata-Version: 2.0
Name: yaraprocessor
Version: 1.1.0
Summary: Scan data streams with Yara using various algorithms.
Home-page: https://github.com/MITRECND/yaraprocessor
Author: Stephen DiCato
Author-email: sdicato@mitre.org
License: Copyright (c) 2013 The MITRE Corporation. All rights reserved.
